{
    "$schema": "https://schema.management.azure.com/schemas/2019-04-01/deploymentTemplate.json#",
    "contentVersion": "1.0.0.0",
    "parameters": {
        "keyVaultName": {
        "type": "string"
        },
        "keyVaultSecretName": {
        "type": "string"
        }
        },
     
    "resources": [] ,

        "outputs": {
        "retrievedSecretValue": {
          "type": "string",
          "value": "[reference(concat('Microsoft.KeyVault/vaults/', parameters('keyVaultName'), '/secrets/', parameters('keyVaultSecretName')), '2019-09-01').value]"
        }
       
      }
}